{"trial_id": "00", "hyperparameters": {"space": [{"class_name": "Int", "config": {"name": "filters", "default": null, "conditions": [], "min_value": 32, "max_value": 128, "step": 32, "sampling": "linear"}}, {"class_name": "Choice", "config": {"name": "kernel_size", "default": 3, "conditions": [], "values": [3, 5, 7], "ordered": true}}, {"class_name": "Int", "config": {"name": "units", "default": null, "conditions": [], "min_value": 32, "max_value": 128, "step": 32, "sampling": "linear"}}, {"class_name": "Choice", "config": {"name": "learning_rate", "default": 0.01, "conditions": [], "values": [0.01, 0.001, 0.0001], "ordered": true}}], "values": {"filters": 128, "kernel_size": 7, "units": 32, "learning_rate": 0.001}}, "metrics": {"metrics": {"accuracy": {"direction": "max", "observations": [{"value": [0.5004482865333557], "step": 8}]}, "loss": {"direction": "min", "observations": [{"value": [0.6931721568107605], "step": 8}]}, "val_accuracy": {"direction": "max", "observations": [{"value": [0.5034005045890808], "step": 8}]}, "val_loss": {"direction": "min", "observations": [{"value": [0.6931353211402893], "step": 8}]}}}, "score": 0.5034005045890808, "best_step": 8, "status": "COMPLETED", "message": null}